zlutils/version.py
zlutils/v1/__init__.py
zlutils/v1/compat/__init__.py
zlutils/v1/framework/__init__.py
zlutils/v1/framework/app.py
zlutils/v1/framework/callback.py
zlutils/v1/framework/config.py
zlutils/v1/framework/event.py
zlutils/v1/framework/example.py
zlutils/v1/framework/lifecycle.py
zlutils/v1/framework/plugin.py
zlutils/v1/framework/Plugins/plugin_example.py
zlutils/v1/typing/__init__.py
zlutils/v1/typing/attribute.py
zlutils/v1/typing/dataitem.py
zlutils/v1/typing/image/__init__.py
zlutils/v1/typing/image/imghdr.py
zlutils/v1/typing/image/no_image.jpg
zlutils/v2/framework.py
zlutils/v2/typing/image.py
zlutils/v2/typing/imghdr.py
zlutils/v2/typing/no_image.jpg
zlutils-1.0.2.dist-info/licenses/LICENSE
zlutils-1.0.2.dist-info/METADATA
zlutils-1.0.2.dist-info/WHEEL
zlutils-1.0.2.dist-info/top_level.txt
zlutils-1.0.2.dist-info/RECORD
