Metadata-Version: 2.4
Name: zlutils
Version: 1.0.2
Summary: a package of utils
Author-email: zlols <zlols@foxmail.com>
License-Expression: MIT
Project-URL: Repository, https://gitee.com/zlols/zlutils.py.git
Classifier: Programming Language :: Python :: 3 :: Only
Requires-Python: >=3.8
License-File: LICENSE
Dynamic: license-file
